hello_joel/__init__.py
hello_joel/hello.py
hello_joel-0.0.5.dist-info/METADATA
hello_joel-0.0.5.dist-info/WHEEL
hello_joel-0.0.5.dist-info/top_level.txt
hello_joel-0.0.5.dist-info/RECORD
